agent_add/__init__.py
agent_add-0.2.0.dist-info/METADATA
agent_add-0.2.0.dist-info/WHEEL
agent_add-0.2.0.dist-info/entry_points.txt
agent_add-0.2.0.dist-info/RECORD
